README.md
setup.py
json_store_client/__init__.py
json_store_client.egg-info/PKG-INFO
json_store_client.egg-info/SOURCES.txt
json_store_client.egg-info/dependency_links.txt
json_store_client.egg-info/requires.txt
json_store_client.egg-info/top_level.txt