Metadata-Version: 2.1
Name: json-store-client
Version: 1.1.0
Summary: A client library for jsonstore
Home-page: https://github.com/leon332157/json-store-client
Author: leon332157
Author-email: leon332157@gmail.com
License: UNKNOWN
Platform: UNKNOWN
Classifier: Programming Language :: Python :: 3.6
Classifier: Programming Language :: Python :: 3.7
Classifier: License :: OSI Approved :: MIT License
Classifier: Operating System :: OS Independent
Classifier: Topic :: Internet
